C4point5/C45.py
C4point5/__init__.py
C4point5-1.0.2.dist-info/LICENSE.txt
C4point5-1.0.2.dist-info/METADATA
C4point5-1.0.2.dist-info/WHEEL
C4point5-1.0.2.dist-info/top_level.txt
C4point5-1.0.2.dist-info/RECORD
