Metadata-Version: 2.1
Name: C4point5
Version: 1.0.2
Summary: An implementation of C4.5 Algorithm
Home-page: https://github.com/nomancseku/C4point5
Author: Abdullah Al Noman
Author-email: nomancseku@gmail.com
License: UNKNOWN
Project-URL: Bug Tracker, https://github.com/nomancseku/C4point5/issues
Platform: UNKNOWN
Classifier: Programming Language :: Python :: 3
Classifier: License :: OSI Approved :: MIT License
Classifier: Operating System :: OS Independent
Requires-Python: >=3.6
